sdb.py
sdb-1.8.dist-info/LICENSE
sdb-1.8.dist-info/METADATA
sdb-1.8.dist-info/WHEEL
sdb-1.8.dist-info/entry_points.txt
sdb-1.8.dist-info/top_level.txt
sdb-1.8.dist-info/RECORD
