Metadata-Version: 2.1
Name: sdb
Version: 1.8
Summary: A socket-based remote debugger for Python
Home-page: https://github.com/ryanpetrello/sdb
Author: Ryan Petrello
Author-email: ryan@ryanpetrello.com
License: UNKNOWN
Platform: UNKNOWN
Classifier: Development Status :: 5 - Production/Stable
Classifier: Environment :: Console
Classifier: Intended Audience :: Developers
Classifier: Intended Audience :: System Administrators
Classifier: License :: OSI Approved :: BSD License
Classifier: Operating System :: MacOS :: MacOS X
Classifier: Operating System :: Microsoft :: Windows
Classifier: Operating System :: POSIX
Classifier: Programming Language :: Python
Classifier: Programming Language :: Python :: 2
Classifier: Programming Language :: Python :: 3
Requires-Dist: pygments
Requires-Dist: six
